{
  "model": {

    "name" : "LSTM",

    "image":
    {
      "image_input": "raw",
      "dim": [224, 224, 3],
      "normalize": true,

      "resnet_version": 50,

      "attention" : {
        "mode": "glimpse",
        "no_attention_mlp": 256,
        "no_glimpses": 2
      },

      "cbn": {
        "use_cbn": true,
        "cbn_embedding_size": 512
      }

    },

    "glove": true,

    "word_embedding_dim": 300,
    "no_hidden_LSTM": 1024,
    "no_LSTM_cell": 1,

    "no_question_mlp": 1024,
    "no_picture_mlp": 1024,

    "no_hidden_final_mlp": 1024,
    "dropout_keep_prob": 0.5,




    "loss": "soft",
    "activation": "tanh",
    "excluded_scope_names": ["resnet_v1_50/conv1", "shortcut"],
    "finetune" : []
  },

  "optimizer": {
    "no_epoch": 15,
    "learning_rate": 3e-4,
    "batch_size": 20,
    "clip_val": 5
  },

  "dico_name" : "dict.json",
  "glove_name" : "glove_dict.pkl",

  "merge_dataset": false,
  "seed": -1
}